{
  "created_at": "Wed Jul 12 06:54:18 +0000 2017",
  "id": 885029531551223808,
  "id_str": "885029531551223808",
  "text": "RT @MartinBelam: Imagine Watergate. But one of Nixon's kids kept uploading all the tapes to Soundcloud",
  "truncated": false,
  "entities": {
    "hashtags": [],
    "symbols": [],
    "user_mentions": [{
      "screen_name": "MartinBelam",
      "name": "Martin Belam",
      "id": 14301286,
      "id_str": "14301286",
      "indices": [3, 15]
    }],
    "urls": []
  },
  "source": "\u003ca href=\"http://twitter.com/download/iphone\" rel=\"nofollow\"\u003eTwitter for iPhone\u003c/a\u003e",
  "in_reply_to_status_id": null,
  "in_reply_to_status_id_str": null,
  "in_reply_to_user_id": null,
  "in_reply_to_user_id_str": null,
  "in_reply_to_screen_name": null,
  "user": {
    "id": 16119189,
    "id_str": "16119189",
    "name": "Daniel Jacob Archer",
    "screen_name": "dja1o",
    "location": "Los Angeles, CA",
    "description": "hacker, designer, bourbon drinker. building product @hootsuite in LA, prev. @naritiv (acq) and in @techstars. super @apple fanboy since 2. #LongLA",
    "url": "https://t.co/iVL4ddx8V0",
    "entities": {
      "url": {
        "urls": [{
          "url": "https://t.co/iVL4ddx8V0",
          "expanded_url": "http://dja.io",
          "display_url": "dja.io",
          "indices": [0, 23]
        }]
      },
      "description": {
        "urls": []
      }
    },
    "protected": false,
    "followers_count": 911,
    "friends_count": 2452,
    "listed_count": 81,
    "created_at": "Wed Sep 03 20:31:58 +0000 2008",
    "favourites_count": 3732,
    "utc_offset": -25200,
    "time_zone": "Pacific Time (US \u0026 Canada)",
    "geo_enabled": true,
    "verified": false,
    "statuses_count": 8717,
    "lang": "en",
    "contributors_enabled": false,
    "is_translator": false,
    "is_translation_enabled": false,
    "profile_background_color": "FFFFFF",
    "profile_background_image_url": "http://pbs.twimg.com/profile_background_images/582161084/0fbb1e8ua9t75axd0twy.png",
    "profile_background_image_url_https": "https://pbs.twimg.com/profile_background_images/582161084/0fbb1e8ua9t75axd0twy.png",
    "profile_background_tile": true,
    "profile_image_url": "http://pbs.twimg.com/profile_images/626585421426749440/H5cij7zH_normal.jpg",
    "profile_image_url_https": "https://pbs.twimg.com/profile_images/626585421426749440/H5cij7zH_normal.jpg",
    "profile_banner_url": "https://pbs.twimg.com/profile_banners/16119189/1403123326",
    "profile_link_color": "00B4FF",
    "profile_sidebar_border_color": "2F5270",
    "profile_sidebar_fill_color": "EDEDED",
    "profile_text_color": "474747",
    "profile_use_background_image": false,
    "has_extended_profile": true,
    "default_profile": false,
    "default_profile_image": false,
    "following": false,
    "follow_request_sent": false,
    "notifications": false,
    "translator_type": "none"
  },
  "geo": null,
  "coordinates": null,
  "place": null,
  "contributors": null,
  "retweeted_status": {
    "created_at": "Tue Jul 11 15:29:02 +0000 2017",
    "id": 884796683267305472,
    "id_str": "884796683267305472",
    "text": "Imagine Watergate. But one of Nixon's kids kept uploading all the tapes to Soundcloud",
    "truncated": false,
    "entities": {
      "hashtags": [],
      "symbols": [],
      "user_mentions": [],
      "urls": []
    },
    "source": "\u003ca href=\"http://twitter.com/download/iphone\" rel=\"nofollow\"\u003eTwitter for iPhone\u003c/a\u003e",
    "in_reply_to_status_id": null,
    "in_reply_to_status_id_str": null,
    "in_reply_to_user_id": null,
    "in_reply_to_user_id_str": null,
    "in_reply_to_screen_name": null,
    "user": {
      "id": 14301286,
      "id_str": "14301286",
      "name": "Martin Belam",
      "screen_name": "MartinBelam",
      "location": "martin.belam@theguardian.com",
      "description": "Social \u0026 New Formats Editor at @Guardian in London. Does a link round-up every Friday https://t.co/tlE2uhRQA5",
      "url": "https://t.co/r2MqdBh0P2",
      "entities": {
        "url": {
          "urls": [{
            "url": "https://t.co/r2MqdBh0P2",
            "expanded_url": "http://martinbelam.com",
            "display_url": "martinbelam.com",
            "indices": [0, 23]
          }]
        },
        "description": {
          "urls": [{
            "url": "https://t.co/tlE2uhRQA5",
            "expanded_url": "http://martinbelam.com/category/friday-reading/",
            "display_url": "martinbelam.com/category/frida…",
            "indices": [86, 109]
          }]
        }
      },
      "protected": false,
      "followers_count": 35178,
      "friends_count": 13315,
      "listed_count": 1460,
      "created_at": "Fri Apr 04 09:50:59 +0000 2008",
      "favourites_count": 42499,
      "utc_offset": 3600,
      "time_zone": "London",
      "geo_enabled": true,
      "verified": true,
      "statuses_count": 91296,
      "lang": "en",
      "contributors_enabled": false,
      "is_translator": false,
      "is_translation_enabled": false,
      "profile_background_color": "FFFFFF",
      "profile_background_image_url": "http://pbs.twimg.com/profile_background_images/662583066/t22fowzg0vi5ezvrc5co.png",
      "profile_background_image_url_https": "https://pbs.twimg.com/profile_background_images/662583066/t22fowzg0vi5ezvrc5co.png",
      "profile_background_tile": true,
      "profile_image_url": "http://pbs.twimg.com/profile_images/882185374495375360/3TtMQFJX_normal.jpg",
      "profile_image_url_https": "https://pbs.twimg.com/profile_images/882185374495375360/3TtMQFJX_normal.jpg",
      "profile_banner_url": "https://pbs.twimg.com/profile_banners/14301286/1498653234",
      "profile_link_color": "00456E",
      "profile_sidebar_border_color": "FFFFFF",
      "profile_sidebar_fill_color": "F5F5F5",
      "profile_text_color": "000000",
      "profile_use_background_image": true,
      "has_extended_profile": true,
      "default_profile": false,
      "default_profile_image": false,
      "following": false,
      "follow_request_sent": false,
      "notifications": false,
      "translator_type": "none"
    },
    "geo": null,
    "coordinates": null,
    "place": null,
    "contributors": null,
    "is_quote_status": false,
    "retweet_count": 22392,
    "favorite_count": 63853,
    "favorited": true,
    "retweeted": true,
    "lang": "en"
  },
  "is_quote_status": false,
  "retweet_count": 22392,
  "favorite_count": 0,
  "favorited": true,
  "retweeted": true,
  "lang": "en"
}
